nbformat_types/__init__.py
nbformat_types/versions/__init__.py
nbformat_types/versions/v3_0.py
nbformat_types/versions/v4_0.py
nbformat_types/versions/v4_1.py
nbformat_types/versions/v4_2.py
nbformat_types/versions/v4_3.py
nbformat_types/versions/v4_4.py
nbformat_types/versions/v4_5.py
nbformat_types-0.1.dist-info/METADATA
nbformat_types-0.1.dist-info/WHEEL
nbformat_types-0.1.dist-info/RECORD
